v2s_common_utils/__init__.py
v2s_common_utils/base_service.py
v2s_common_utils/constants.py
v2s_common_utils/custom_validations.py
v2s_common_utils/decorators.py
v2s_common_utils/errors.py
v2s_common_utils/exceptions.py
v2s_common_utils/logger.py
v2s_common_utils/message.py
v2s_common_utils/pagination.py
v2s_common_utils/swagger.py
v2s_common_utils/utils.py
v2s_common_utils/validations.py
v2s_common_utils-1.0.0.dist-info/METADATA
v2s_common_utils-1.0.0.dist-info/WHEEL
v2s_common_utils-1.0.0.dist-info/top_level.txt
v2s_common_utils-1.0.0.dist-info/RECORD
